<Parameters xmlns="http://hl7.org/fhir">
  <id value="4r2lLa6InH"/>
  <meta>
    <versionId value="rH4ejuUUC9"/>
    <lastUpdated value="2019-08-08T09:17:30.279-04:00"/>
    <source value="vNoiIHchXD"/>
    <profile value="RCJ957Eb4o"/>
    <security>
      <system value="wyhQ4lVSkp"/>
      <version value="Iag5Ueb0pR"/>
      <code value="7m9349dVcd"/>
      <display value="5bxaJPofaI"/>
      <userSelected value="true"/>
    </security>
    <tag>
      <system value="C_pq_o6Q9n"/>
      <version value="QqNvI7JwM1"/>
      <code value="jIh0OIpcFD"/>
      <display value="g1ekbw_YFy"/>
      <userSelected value="true"/>
    </tag>
    <tag>
      <code value="ibm/complete-mock"/>
    </tag>
  </meta>
  <implicitRules value="ZSRKDOYY_d"/>
  <language value="Dgy7xmtKKz"/>
  <parameter>
    <name value="c5xHtbrJkZ"/>
    <valueUuid value="urn:uuid:309b5dc9-4e58-4d48-b458-20643fb4ebb3"/>
  </parameter>
</Parameters>