<Parameters xmlns="http://hl7.org/fhir">
  <meta>
    <versionId value="pKWoB8Ih7q"/>
    <lastUpdated value="2020-11-04T02:37:49.481852-05:00"/>
    <source value="7zFFtYz3Z3"/>
    <profile value="YMBegDhn3w"/>
    <security>
      <system value="sQqbfeGt_Z"/>
      <version value="C2p2OMHbSL"/>
      <code value="raKUghm3ku"/>
      <display value="eDYuQgU66l"/>
      <userSelected value="true"/>
    </security>
    <tag>
      <system value="GgRZ2GWlYB"/>
      <version value="3qO91SDMrR"/>
      <code value="mfLjXuJKPG"/>
      <display value="B_sBAAjtv5"/>
      <userSelected value="true"/>
    </tag>
    <tag>
      <code value="ibm/complete-mock"/>
    </tag>
  </meta>
  <implicitRules value="682Nibikme"/>
  <language value="en-US"/>
  <parameter>
    <name value="Ig0AM_7uyW"/>
    <valueUnsignedInt value="1096709232"/>
  </parameter>
</Parameters>