<Parameters xmlns="http://hl7.org/fhir">
  <id value="ONPXvAUTn6"/>
  <meta>
    <versionId value="OuKxXfrYtv"/>
    <lastUpdated value="2019-08-08T09:17:30.297-04:00"/>
    <source value="E7zg4PHKwa"/>
    <profile value="xX6zq1JC7w"/>
    <security>
      <system value="9FHgokLhuq"/>
      <version value="f4jP7DS2y2"/>
      <code value="M8zXbDhLJP"/>
      <display value="kL16kxNZ9C"/>
      <userSelected value="true"/>
    </security>
    <tag>
      <system value="4x9YNvdOl6"/>
      <version value="wEQIpiqs7U"/>
      <code value="ABcQxf5kJp"/>
      <display value="kfCTAPJx1v"/>
      <userSelected value="true"/>
    </tag>
    <tag>
      <code value="ibm/complete-mock"/>
    </tag>
  </meta>
  <implicitRules value="G2nOHmrKSi"/>
  <language value="JAedVQfmvd"/>
  <parameter>
    <name value="v8lEFDk4qS"/>
    <valueId value="p2gMKdOWQT"/>
  </parameter>
</Parameters>