<Parameters xmlns="http://hl7.org/fhir">
  <meta>
    <versionId value="PXmve67Qcu"/>
    <lastUpdated value="2021-03-29T14:45:15.812703-04:00"/>
    <source value="lA1K5Yyhvo"/>
    <profile value="qlv6k9HGj3"/>
    <security>
      <system value="fn9v0J7uWK"/>
      <version value="2QVTNXkYzK"/>
      <code value="_WxiLJg4lE"/>
      <display value="OLEKys0yVO"/>
      <userSelected value="true"/>
    </security>
    <tag>
      <system value="EdExSXDiUV"/>
      <version value="fEJr3M1_9d"/>
      <code value="2c5XtUoI8w"/>
      <display value="Y1rvYvtKWh"/>
      <userSelected value="true"/>
    </tag>
    <tag>
      <code value="ibm/complete-mock"/>
    </tag>
  </meta>
  <implicitRules value="ylbGam0Oq0"/>
  <language value="en-US"/>
  <parameter>
    <name value="o78SChjZCn"/>
    <valueBoolean value="true"/>
  </parameter>
</Parameters>