<Parameters xmlns="http://hl7.org/fhir">
  <meta>
    <versionId value="WqhhivfrWG"/>
    <lastUpdated value="2019-12-04T21:42:35.417-05:00"/>
    <source value="BpeC0l2XPq"/>
    <profile value="MEOJ6lFNw4"/>
    <security>
      <system value="DtlubJamdq"/>
      <version value="AeDTQcTgog"/>
      <code value="yiZatdDR3g"/>
      <display value="Zc9pCLAM56"/>
      <userSelected value="true"/>
    </security>
    <tag>
      <system value="2XWPutWHjp"/>
      <version value="9iPajfSlaJ"/>
      <code value="mRnea27SfW"/>
      <display value="zzd9SBzMnm"/>
      <userSelected value="true"/>
    </tag>
    <tag>
      <code value="ibm/complete-mock"/>
    </tag>
  </meta>
  <implicitRules value="SnLFvQXXar"/>
  <language value="wFSRQf3PWj"/>
  <parameter>
    <name value="iKQsYp4qkn"/>
    <valueBase64Binary value="H00Of1Y="/>
  </parameter>
</Parameters>