<Parameters xmlns="http://hl7.org/fhir">
  <meta>
    <versionId value="fUYCaZlsZh"/>
    <lastUpdated value="2019-12-04T21:42:35.455-05:00"/>
    <source value="gymTOrJEuT"/>
    <profile value="Oi8M3JPH7j"/>
    <security>
      <system value="G3vlaOMGCC"/>
      <version value="DSUYXNWtQH"/>
      <code value="NL0KTEstyO"/>
      <display value="qYhxwF_rqo"/>
      <userSelected value="true"/>
    </security>
    <tag>
      <system value="rPRaEzajee"/>
      <version value="ErJ32pE6AT"/>
      <code value="jgQclFmaZ2"/>
      <display value="Z78xGxt9aW"/>
      <userSelected value="true"/>
    </tag>
    <tag>
      <code value="ibm/complete-mock"/>
    </tag>
  </meta>
  <implicitRules value="VOdbHP0bVE"/>
  <language value="9e_hkWLAXE"/>
  <parameter>
    <name value="PyrIf6Kw7v"/>
    <valueCanonical value="5lhy7UbeHr"/>
  </parameter>
</Parameters>