<Parameters xmlns="http://hl7.org/fhir">
  <meta>
    <versionId value="FyHQGxICa1"/>
    <lastUpdated value="2021-12-10T02:40:14.0648-05:00"/>
    <source value="8dt6f_RhXs"/>
    <profile value="gyHd45YQ3k"/>
    <security>
      <system value="saO7lnog71"/>
      <version value="wdMuvpiJOp"/>
      <code value="HOIriMCKSY"/>
      <display value="f4iOUUajZj"/>
      <userSelected value="true"/>
    </security>
    <tag>
      <system value="MNI6uNhEJP"/>
      <version value="RD168izDpl"/>
      <code value="suV9CpvLwn"/>
      <display value="hW_SemgTY2"/>
      <userSelected value="true"/>
    </tag>
    <tag>
      <code value="ibm/complete-mock"/>
    </tag>
  </meta>
  <implicitRules value="dxv7m_aEgL"/>
  <language value="en-US"/>
  <parameter>
    <name value="4bjDUGXdx9"/>
    <valuePositiveInt value="665512949"/>
  </parameter>
</Parameters>