<SubstanceSourceMaterial xmlns="http://hl7.org/fhir">
  <meta>
    <versionId value="roTek-KMJp"/>
    <lastUpdated value="2021-03-30T15:28:23.16764-04:00"/>
    <source value="5iAB3S2ZkE"/>
    <profile value="3Pqk46iqlq"/>
    <security>
      <system value="WrksebUL8S"/>
      <version value="nWPXpSrEio"/>
      <code value="NqMBKF1iej"/>
      <display value="aDqvR09s5U"/>
      <userSelected value="true"/>
    </security>
    <tag>
      <system value="8k6zgtqdZ7"/>
      <version value="B9uIUDmsHe"/>
      <code value="Ua8v2vk36_"/>
      <display value="C1tifIJiX0"/>
      <userSelected value="true"/>
    </tag>
    <tag>
      <code value="ibm/complete-mock"/>
    </tag>
  </meta>
  <implicitRules value="twJSjPGJrB"/>
  <language value="en-US"/>
  <text>
    <status value="additional"/>
    <div xmlns="http://www.w3.org/1999/xhtml"></div>
  </text>
  <sourceMaterialClass>
    <coding>
      <system value="R8UeYBubwD"/>
      <version value="9V6Ky9a7g1"/>
      <code value="dLPAZLkupz"/>
      <display value="JW1WV8A4JQ"/>
      <userSelected value="true"/>
    </coding>
    <text value="qmViWAVUQ3"/>
  </sourceMaterialClass>
  <sourceMaterialType>
    <coding>
      <system value="2Gef6HzYfi"/>
      <version value="hT5iy7c5JG"/>
      <code value="JX1MJckSNV"/>
      <display value="EfdRRE3jtj"/>
      <userSelected value="true"/>
    </coding>
    <text value="d1GBOJRRC7"/>
  </sourceMaterialType>
  <sourceMaterialState>
    <coding>
      <system value="R9cocCmKH8"/>
      <version value="fBor40qquX"/>
      <code value="j6tzMQ0S2u"/>
      <display value="DkYGVO_nAs"/>
      <userSelected value="true"/>
    </coding>
    <text value="aAcQiK_G89"/>
  </sourceMaterialState>
  <organismId>
    <use value="old"/>
    <type>
      <coding>
        <system value="a1v1B09KVp"/>
        <version value="MDHvFuHqzz"/>
        <code value="nDMA3ypXu3"/>
        <display value="lDs6rtLQM7"/>
        <userSelected value="true"/>
      </coding>
      <text value="xbxg67C0BU"/>
    </type>
    <system value="h98pHxaAeN"/>
    <value value="YyewbwVxbo"/>
    <period>
      <start value="2021-03-30T15:28:23.172118-04:00"/>
      <end value="2021-03-30T15:28:23.17244-04:00"/>
    </period>
  </organismId>
  <organismName value="K9pO0s2mUB"/>
  <parentSubstanceId>
    <use value="old"/>
    <type>
      <coding>
        <system value="iG2Zz0ee21"/>
        <version value="T3Z70aBnXu"/>
        <code value="SGRdy3c0Ce"/>
        <display value="loRVX2a79o"/>
        <userSelected value="true"/>
      </coding>
      <text value="dK9TPsSk8b"/>
    </type>
    <system value="VXaWqBMMrn"/>
    <value value="NLnLC3Em5j"/>
    <period>
      <start value="2021-03-30T15:28:23.174129-04:00"/>
      <end value="2021-03-30T15:28:23.174306-04:00"/>
    </period>
  </parentSubstanceId>
  <parentSubstanceName value="_xuPf8lCgk"/>
  <countryOfOrigin>
    <coding>
      <system value="X4FExVfomC"/>
      <version value="lLKA6nJvD3"/>
      <code value="pi1ponMs6i"/>
      <display value="BhLPViFEY4"/>
      <userSelected value="true"/>
    </coding>
    <text value="G9T0wC92cF"/>
  </countryOfOrigin>
  <geographicalLocation value="7Ar0jgFG1B"/>
  <developmentStage>
    <coding>
      <system value="9j_34GyggS"/>
      <version value="OPGQCV7SNx"/>
      <code value="94yKDx28oR"/>
      <display value="nAzGHwdUtx"/>
      <userSelected value="true"/>
    </coding>
    <text value="j1CAFEd8o3"/>
  </developmentStage>
  <fractionDescription>
    <fraction value="mCRitd_keP"/>
    <materialType>
      <coding>
        <system value="xOIoLqqf8x"/>
        <version value="iemnv18qvs"/>
        <code value="MqFTTKfd5a"/>
        <display value="yB9Gf_SMnd"/>
        <userSelected value="true"/>
      </coding>
      <text value="MdoWX5Wgci"/>
    </materialType>
  </fractionDescription>
  <organism>
    <family>
      <coding>
        <system value="D8KxfLUG_l"/>
        <version value="Glw1MwmvBk"/>
        <code value="YneHDWGn49"/>
        <display value="Lh1quf1mDM"/>
        <userSelected value="true"/>
      </coding>
      <text value="16yS5A8qhs"/>
    </family>
    <genus>
      <coding>
        <system value="LX0PhTYQjJ"/>
        <version value="AIfuxsk8f4"/>
        <code value="GDrxQnbdpf"/>
        <display value="6jzgc8Yclj"/>
        <userSelected value="true"/>
      </coding>
      <text value="xKVzwxFnOQ"/>
    </genus>
    <species>
      <coding>
        <system value="tYYnR5pw0b"/>
        <version value="ro0nu4RqGg"/>
        <code value="M7c8Btlltv"/>
        <display value="mcwfQVnuO0"/>
        <userSelected value="true"/>
      </coding>
      <text value="e3maVJ1GcG"/>
    </species>
    <intraspecificType>
      <coding>
        <system value="c5RQUHnzpQ"/>
        <version value="dLdhDB_mmj"/>
        <code value="vJQ65ZMSu_"/>
        <display value="GTJI9fslQE"/>
        <userSelected value="true"/>
      </coding>
      <text value="jobGlBOKQv"/>
    </intraspecificType>
    <intraspecificDescription value="IMeIERzWn3"/>
    <author>
      <authorType>
        <coding>
          <system value="m56QgDQioi"/>
          <version value="sLnto44kz_"/>
          <code value="IobsSsNqHp"/>
          <display value="WXC99oLRx1"/>
          <userSelected value="true"/>
        </coding>
        <text value="cgpX3jPAM6"/>
      </authorType>
      <authorDescription value="vwS3d0Ev_k"/>
    </author>
    <hybrid>
      <maternalOrganismId value="o1ANwPyB5e"/>
      <maternalOrganismName value="aCn996eIAP"/>
      <paternalOrganismId value="9hUVjZ43i7"/>
      <paternalOrganismName value="Rbsh9m5RxC"/>
      <hybridType>
        <coding>
          <system value="jCHfHIV_sC"/>
          <version value="VQf4rm1tmy"/>
          <code value="M8zaCGEZMc"/>
          <display value="h8avHAGEi4"/>
          <userSelected value="true"/>
        </coding>
        <text value="lGOaTVbjYy"/>
      </hybridType>
    </hybrid>
    <organismGeneral>
      <kingdom>
        <coding>
          <system value="ZFt0WjN0YY"/>
          <version value="ZWCjJlPkg4"/>
          <code value="uWvildtynv"/>
          <display value="3gb4tpIqKe"/>
          <userSelected value="true"/>
        </coding>
        <text value="OeQJ3XWTfx"/>
      </kingdom>
      <phylum>
        <coding>
          <system value="Oxp63Eor6e"/>
          <version value="gr9cVQQXYe"/>
          <code value="u3vmgDwW4G"/>
          <display value="t4DSxB0GZ0"/>
          <userSelected value="true"/>
        </coding>
        <text value="W7KXvcrvkN"/>
      </phylum>
      <class>
        <coding>
          <system value="Za5XSorpOy"/>
          <version value="CGf9i_os2t"/>
          <code value="h6yHweaegn"/>
          <display value="fBq7OLVKsu"/>
          <userSelected value="true"/>
        </coding>
        <text value="FrP4hwgsrm"/>
      </class>
      <order>
        <coding>
          <system value="uvzw5tLvbn"/>
          <version value="CTBVg6_0eb"/>
          <code value="I4JeozTcHV"/>
          <display value="OnXynVpqnq"/>
          <userSelected value="true"/>
        </coding>
        <text value="yZzaPmca5s"/>
      </order>
    </organismGeneral>
  </organism>
  <partDescription>
    <part>
      <coding>
        <system value="dnXw6x9IcB"/>
        <version value="VjwQVXPQLI"/>
        <code value="HcxVJ0_as5"/>
        <display value="c6Ggqxi7nV"/>
        <userSelected value="true"/>
      </coding>
      <text value="IrxeGTCcQT"/>
    </part>
    <partLocation>
      <coding>
        <system value="yLAAvYMcUu"/>
        <version value="ckZQTetI98"/>
        <code value="VHSBKF_qWs"/>
        <display value="ZwdhLa4Tle"/>
        <userSelected value="true"/>
      </coding>
      <text value="CuisB4vQcO"/>
    </partLocation>
  </partDescription>
</SubstanceSourceMaterial>