{
    "resourceType": "CoverageEligibilityRequest",
    "meta": {
        "versionId": "rgqistZRvc",
        "lastUpdated": "2021-03-30T15:28:16.136458-04:00",
        "source": "539WRQ6NR_",
        "profile": [
            "AkCzhcJpNg"
        ],
        "security": [
            {
                "system": "GTPR0LkaAX",
                "version": "wD8_7n95wC",
                "code": "qMBmEp_klU",
                "display": "7tw9kv_IMi",
                "userSelected": true
            }
        ],
        "tag": [
            {
                "system": "941Zpxpz1a",
                "version": "a0z6lBayof",
                "code": "5cLzvoLE4E",
                "display": "2kjqcgmdJR",
                "userSelected": true
            },
            {
                "code": "ibm/complete-mock"
            }
        ]
    },
    "implicitRules": "JM7Pcz3heP",
    "language": "en-US",
    "text": {
        "status": "empty",
        "div": "<div xmlns=\"http://www.w3.org/1999/xhtml\"></div>"
    },
    "identifier": [
        {
            "use": "secondary",
            "type": {
                "coding": [
                    {
                        "system": "DPe668Ii88",
                        "version": "xjo33PHVd9",
                        "code": "37yRqSj88m",
                        "display": "0WqLqmCkJw",
                        "userSelected": true
                    }
                ],
                "text": "O_Zrxfo6BJ"
            },
            "system": "FHuWfvuFAA",
            "value": "RFNiyeMMGS",
            "period": {
                "start": "2021-03-30T15:28:16.13899-04:00",
                "end": "2021-03-30T15:28:16.139169-04:00"
            }
        }
    ],
    "status": "active",
    "priority": {
        "coding": [
            {
                "system": "AaqPD5b3sp",
                "version": "KmX_c3HhUZ",
                "code": "p_bTioXAyL",
                "display": "m2ebZ6rmf7",
                "userSelected": true
            }
        ],
        "text": "D_eaKGNloM"
    },
    "purpose": [
        "benefits"
    ],
    "patient": {
        "reference": "Patient/iqRGdRsRSZ",
        "type": "Patient",
        "identifier": {
            "use": "old",
            "type": {
                "coding": [
                    {
                        "system": "eDZC7azx3w",
                        "version": "kgTkU0gTfY",
                        "code": "DAjjdloZsO",
                        "display": "slR3yXSduc",
                        "userSelected": true
                    }
                ],
                "text": "lOn6tfr36i"
            },
            "system": "lx_asPn8zf",
            "value": "nJyTqHurBf",
            "period": {
                "start": "2021-03-30T15:28:16.140713-04:00",
                "end": "2021-03-30T15:28:16.140885-04:00"
            }
        },
        "display": "GdPJCxrznM"
    },
    "servicedDate": "2021-03-30",
    "created": "2021-03-30T15:28:16.141351-04:00",
    "enterer": {
        "reference": "Practitioner/uNziLRhyyt",
        "type": "Practitioner",
        "identifier": {
            "use": "usual",
            "type": {
                "coding": [
                    {
                        "system": "bpVhBNUIEz",
                        "version": "F7Bn8u8H7p",
                        "code": "_qkjve70Ex",
                        "display": "0fyqkFUp9A",
                        "userSelected": true
                    }
                ],
                "text": "qxSPZ5eCz2"
            },
            "system": "ryva3XR7JC",
            "value": "S4coy2dkii",
            "period": {
                "start": "2021-03-30T15:28:16.142399-04:00",
                "end": "2021-03-30T15:28:16.142576-04:00"
            }
        },
        "display": "bQiIKoiSDv"
    },
    "provider": {
        "reference": "Practitioner/Ezv9KAhFGE",
        "type": "Practitioner",
        "identifier": {
            "use": "temp",
            "type": {
                "coding": [
                    {
                        "system": "B3PFT06s9g",
                        "version": "hFUg4VjtIg",
                        "code": "MvPeu8pqb7",
                        "display": "nAIUvyJUpW",
                        "userSelected": true
                    }
                ],
                "text": "Et3sBOOe5R"
            },
            "system": "ws0TvjevtB",
            "value": "IRkdxQyBY8",
            "period": {
                "start": "2021-03-30T15:28:16.143646-04:00",
                "end": "2021-03-30T15:28:16.14382-04:00"
            }
        },
        "display": "eOfbKKrvMi"
    },
    "insurer": {
        "reference": "Organization/hiLXRwgq3r",
        "type": "Organization",
        "identifier": {
            "use": "official",
            "type": {
                "coding": [
                    {
                        "system": "cv65rBcKyG",
                        "version": "DypK4qnPB4",
                        "code": "MEGszLY8Td",
                        "display": "4fU_W2yl9j",
                        "userSelected": true
                    }
                ],
                "text": "Adb7zDXzJS"
            },
            "system": "AHjxB6bnOg",
            "value": "QVLDbp_1iv",
            "period": {
                "start": "2021-03-30T15:28:16.144862-04:00",
                "end": "2021-03-30T15:28:16.145029-04:00"
            }
        },
        "display": "lbDdl6KY5A"
    },
    "facility": {
        "reference": "Location/m2i3vS1qTW",
        "type": "Location",
        "identifier": {
            "use": "official",
            "type": {
                "coding": [
                    {
                        "system": "Zu4aNkSD0W",
                        "version": "LXPGDkkt8R",
                        "code": "DNRHfAJ4J5",
                        "display": "JIaHcfFZC1",
                        "userSelected": true
                    }
                ],
                "text": "yUXEIvHlF8"
            },
            "system": "ZqgnmWYUqb",
            "value": "nOhTtaZyds",
            "period": {
                "start": "2021-03-30T15:28:16.146036-04:00",
                "end": "2021-03-30T15:28:16.146198-04:00"
            }
        },
        "display": "5_XLjxH7KW"
    },
    "supportingInfo": [
        {
            "sequence": 63464940,
            "information": {
                "reference": "Basic/dqK67rw0FK",
                "type": "Basic",
                "identifier": {
                    "use": "temp",
                    "type": {
                        "coding": [
                            {
                                "system": "wxgcpP_MOp",
                                "version": "rnyKXgJEx5",
                                "code": "1CAODcTXB5",
                                "display": "WhFMcOAeEb",
                                "userSelected": true
                            }
                        ],
                        "text": "2iSi9V34WL"
                    },
                    "system": "04_dyjjzlW",
                    "value": "CxpQizkzHo",
                    "period": {
                        "start": "2021-03-30T15:28:16.147789-04:00",
                        "end": "2021-03-30T15:28:16.147978-04:00"
                    }
                },
                "display": "U_WGSvzAac"
            },
            "appliesToAll": true
        }
    ],
    "insurance": [
        {
            "focal": true,
            "coverage": {
                "reference": "Coverage/lSYMy6uZGI",
                "type": "Coverage",
                "identifier": {
                    "use": "old",
                    "type": {
                        "coding": [
                            {
                                "system": "DiBIY9Y2RF",
                                "version": "1_mf894_XZ",
                                "code": "jrH7jY0LPo",
                                "display": "LG4g6Fq5BS",
                                "userSelected": true
                            }
                        ],
                        "text": "sbcL40URKJ"
                    },
                    "system": "YjFzUWTwlR",
                    "value": "3VFsMGfjMA",
                    "period": {
                        "start": "2021-03-30T15:28:16.149399-04:00",
                        "end": "2021-03-30T15:28:16.149574-04:00"
                    }
                },
                "display": "W2S3R39Xhm"
            },
            "businessArrangement": "rdY6gRY3J0"
        }
    ],
    "item": [
        {
            "supportingInfoSequence": [
                1080904005
            ],
            "category": {
                "coding": [
                    {
                        "system": "37v2qhLC6r",
                        "version": "0AxEGtR0Ij",
                        "code": "lJ5Dk4azu8",
                        "display": "r6LfwQxGd0",
                        "userSelected": true
                    }
                ],
                "text": "QltTq83Asf"
            },
            "productOrService": {
                "coding": [
                    {
                        "system": "4kvWhKriTQ",
                        "version": "HS9GArXeWE",
                        "code": "hrt5EXaO7z",
                        "display": "oxUIoYnDMZ",
                        "userSelected": true
                    }
                ],
                "text": "hMgb2sWDFH"
            },
            "modifier": [
                {
                    "coding": [
                        {
                            "system": "rml0b5eh5P",
                            "version": "ZNce2147Pt",
                            "code": "UP2dHvol0j",
                            "display": "rFJneKowOg",
                            "userSelected": true
                        }
                    ],
                    "text": "Sr3eSF7CJh"
                }
            ],
            "provider": {
                "reference": "Practitioner/mB613DR6lT",
                "type": "Practitioner",
                "identifier": {
                    "use": "official",
                    "type": {
                        "coding": [
                            {
                                "system": "4g4ONiKfhs",
                                "version": "EEH20B7yWu",
                                "code": "HyoUQ3Ofjh",
                                "display": "A3pA6moajy",
                                "userSelected": true
                            }
                        ],
                        "text": "INIQT9aRKm"
                    },
                    "system": "_hekA9bV4g",
                    "value": "7cSSaFed8I",
                    "period": {
                        "start": "2021-03-30T15:28:16.152576-04:00",
                        "end": "2021-03-30T15:28:16.15276-04:00"
                    }
                },
                "display": "NNA2OHaqyA"
            },
            "quantity": {
                "value": 0.0205857435878964122044632034658206976018846035003662109375,
                "unit": "sH9I7XuS8D",
                "system": "jike3_7Hp1",
                "code": "C0yCrLtewi"
            },
            "unitPrice": {
                "value": 0.521441245553657228839483650517649948596954345703125,
                "currency": "JgUOdt2p5d"
            },
            "facility": {
                "reference": "Location/6lp3ewk7PM",
                "type": "Location",
                "identifier": {
                    "use": "usual",
                    "type": {
                        "coding": [
                            {
                                "system": "DEoZrTmRQ6",
                                "version": "LMsXhpqjSe",
                                "code": "6gbxLU3svz",
                                "display": "CQtTMVRTDo",
                                "userSelected": true
                            }
                        ],
                        "text": "CkfgjTURyY"
                    },
                    "system": "9jLHNjCZzt",
                    "value": "yhxkeahPK2",
                    "period": {
                        "start": "2021-03-30T15:28:16.154688-04:00",
                        "end": "2021-03-30T15:28:16.154861-04:00"
                    }
                },
                "display": "iO4jTU7lPO"
            },
            "diagnosis": [
                {
                    "diagnosisCodeableConcept": {
                        "coding": [
                            {
                                "system": "P7lf3aS3gK",
                                "version": "f7C3b9yfiW",
                                "code": "2K2uMyzo9E",
                                "display": "ch16GPp4_w",
                                "userSelected": true
                            }
                        ],
                        "text": "7OYGThmVqW"
                    }
                }
            ],
            "detail": [
                {
                    "reference": "Basic/IFSdrNpM_A",
                    "type": "Basic",
                    "identifier": {
                        "use": "old",
                        "type": {
                            "coding": [
                                {
                                    "system": "KAJ4xK635z",
                                    "version": "DFgUlSSrDE",
                                    "code": "0O_PM5xBcS",
                                    "display": "AQVoBHalKs",
                                    "userSelected": true
                                }
                            ],
                            "text": "407aHv1JPn"
                        },
                        "system": "iN9KxKUgvQ",
                        "value": "2oqtuKM22X",
                        "period": {
                            "start": "2021-03-30T15:28:16.156627-04:00",
                            "end": "2021-03-30T15:28:16.156816-04:00"
                        }
                    },
                    "display": "d9Muhrm2LI"
                }
            ]
        }
    ]
}