{
    "resourceType": "MedicationStatement",
    "meta": {
        "versionId": "u46jHugGTo",
        "lastUpdated": "2021-03-29T10:12:04.972337-04:00",
        "source": "zCbKaeT5q8",
        "profile": [
            "iZgDp8Z7t5"
        ],
        "security": [
            {
                "system": "UCGpXzRi2r",
                "version": "GEwNn186e4",
                "code": "JBHSmkrbSN",
                "display": "0m713mJtuz",
                "userSelected": true
            }
        ],
        "tag": [
            {
                "system": "zLcu7EgKmb",
                "version": "yJyzIS2Tst",
                "code": "t9ZLn7K1dS",
                "display": "GKM_GadkmF",
                "userSelected": true
            },
            {
                "code": "ibm/complete-mock"
            }
        ]
    },
    "implicitRules": "L0D_TGf4N6",
    "language": "en-US",
    "text": {
        "status": "additional",
        "div": "<div xmlns=\"http://www.w3.org/1999/xhtml\"></div>"
    },
    "identifier": [
        {
            "use": "official",
            "type": {
                "coding": [
                    {
                        "system": "RJ9rSMFNSs",
                        "version": "I9hWryHcdu",
                        "code": "jfwaK0SPLV",
                        "display": "87FYkyR4Ai",
                        "userSelected": true
                    }
                ],
                "text": "R4hh4bzUNY"
            },
            "system": "ncgW2oLnmc",
            "value": "8jWGhEtnTi",
            "period": {
                "start": "2021-03-29T10:12:04.974908-04:00",
                "end": "2021-03-29T10:12:04.975083-04:00"
            }
        }
    ],
    "basedOn": [
        {
            "reference": "MedicationRequest/vAyAUwWMwY",
            "type": "MedicationRequest",
            "identifier": {
                "use": "usual",
                "type": {
                    "coding": [
                        {
                            "system": "rI6txGpMjn",
                            "version": "HEXWY6H4Gj",
                            "code": "jePpMXHPWr",
                            "display": "eiClnc5kPu",
                            "userSelected": true
                        }
                    ],
                    "text": "xlpWFRNk4f"
                },
                "system": "I7FTSd9E8S",
                "value": "tNxJWA1QZY",
                "period": {
                    "start": "2021-03-29T10:12:04.976005-04:00",
                    "end": "2021-03-29T10:12:04.976162-04:00"
                }
            },
            "display": "jhybi2wxhr"
        }
    ],
    "partOf": [
        {
            "reference": "MedicationAdministration/cZHyTVIWHV",
            "type": "MedicationAdministration",
            "identifier": {
                "use": "official",
                "type": {
                    "coding": [
                        {
                            "system": "zwX2efl70I",
                            "version": "ynC8_bGxfc",
                            "code": "jg_9z7LdeY",
                            "display": "VGLQ9AvIQR",
                            "userSelected": true
                        }
                    ],
                    "text": "BOARicI9wq"
                },
                "system": "XbaQWc1bvC",
                "value": "_AyGEiwpdP",
                "period": {
                    "start": "2021-03-29T10:12:04.977113-04:00",
                    "end": "2021-03-29T10:12:04.977268-04:00"
                }
            },
            "display": "4tG4OlQ6Jg"
        }
    ],
    "status": "on-hold",
    "statusReason": [
        {
            "coding": [
                {
                    "system": "wzu1PrBrcM",
                    "version": "wAYEwiK5UU",
                    "code": "h1_LdUYrjc",
                    "display": "lx_7pPRt3C",
                    "userSelected": true
                }
            ],
            "text": "qjBYg6cknK"
        }
    ],
    "category": {
        "coding": [
            {
                "system": "Cdg6fHmC3L",
                "version": "zfWHTCCjHI",
                "code": "37TqfCQabF",
                "display": "Ilz8kaJbvs",
                "userSelected": true
            }
        ],
        "text": "_Xe_vXrdv4"
    },
    "medicationReference": {
        "reference": "Medication/d0LTxMabqF",
        "type": "Medication",
        "identifier": {
            "use": "official",
            "type": {
                "coding": [
                    {
                        "system": "TtUCZ4FAMs",
                        "version": "JC74cKRDMf",
                        "code": "B1RktpfU1D",
                        "display": "FdgJ6DVEcK",
                        "userSelected": true
                    }
                ],
                "text": "x2AfsNSzK1"
            },
            "system": "ntpJUORjyr",
            "value": "G8wOxJLLqP",
            "period": {
                "start": "2021-03-29T10:12:04.979052-04:00",
                "end": "2021-03-29T10:12:04.97921-04:00"
            }
        },
        "display": "cxVqrna7mi"
    },
    "subject": {
        "reference": "Group/bAH6YVj87T",
        "type": "Group",
        "identifier": {
            "use": "usual",
            "type": {
                "coding": [
                    {
                        "system": "zsEicTI5Tk",
                        "version": "P16AHRMAr9",
                        "code": "Zfq1zKsvjo",
                        "display": "maDgmVbYnX",
                        "userSelected": true
                    }
                ],
                "text": "qweYxSZ05P"
            },
            "system": "G1hbpESkK6",
            "value": "x5NZLDU1oA",
            "period": {
                "start": "2021-03-29T10:12:04.980197-04:00",
                "end": "2021-03-29T10:12:04.980361-04:00"
            }
        },
        "display": "O_y4wDxwpx"
    },
    "context": {
        "reference": "EpisodeOfCare/COaGFkq6PH",
        "type": "EpisodeOfCare",
        "identifier": {
            "use": "temp",
            "type": {
                "coding": [
                    {
                        "system": "Ih2ynhhlLV",
                        "version": "wjqmUfVys1",
                        "code": "NA8nFIHl42",
                        "display": "pYcTheDL4n",
                        "userSelected": true
                    }
                ],
                "text": "7MvN3tZDfz"
            },
            "system": "FgV1vd_Cdy",
            "value": "XviMUtW74O",
            "period": {
                "start": "2021-03-29T10:12:04.981521-04:00",
                "end": "2021-03-29T10:12:04.981708-04:00"
            }
        },
        "display": "tiUN5UV8xQ"
    },
    "effectivePeriod": {
        "start": "2021-03-29T10:12:04.981953-04:00",
        "end": "2021-03-29T10:12:04.982107-04:00"
    },
    "dateAsserted": "2021-03-29T10:12:04.982257-04:00",
    "informationSource": {
        "reference": "Patient/qThz2SX56g",
        "type": "Patient",
        "identifier": {
            "use": "old",
            "type": {
                "coding": [
                    {
                        "system": "uM6CwH9AUp",
                        "version": "H1PZzD5Kyt",
                        "code": "ib3sh9bMyV",
                        "display": "3p26yFlzEt",
                        "userSelected": true
                    }
                ],
                "text": "BEB1fyW6Xh"
            },
            "system": "VQMRXo717N",
            "value": "cO9naFItBW",
            "period": {
                "start": "2021-03-29T10:12:04.983159-04:00",
                "end": "2021-03-29T10:12:04.983314-04:00"
            }
        },
        "display": "Hoc3_rd33j"
    },
    "derivedFrom": [
        {
            "reference": "Basic/LME5Zhh6_e",
            "type": "Basic",
            "identifier": {
                "use": "usual",
                "type": {
                    "coding": [
                        {
                            "system": "qjnGw3wMUO",
                            "version": "qJEocdreIq",
                            "code": "oTi8ik0s_1",
                            "display": "woqLAI3tp9",
                            "userSelected": true
                        }
                    ],
                    "text": "cAcX5ZsEZx"
                },
                "system": "xWsQUubHgp",
                "value": "x15z_qGbPu",
                "period": {
                    "start": "2021-03-29T10:12:04.984529-04:00",
                    "end": "2021-03-29T10:12:04.984696-04:00"
                }
            },
            "display": "cMg9mzaWNI"
        }
    ],
    "reasonCode": [
        {
            "coding": [
                {
                    "system": "KhJu5t0rFv",
                    "version": "m6xgi7gaLC",
                    "code": "0vnPzQACHk",
                    "display": "L1gtVBzzpa",
                    "userSelected": true
                }
            ],
            "text": "uZvQb380Zz"
        }
    ],
    "reasonReference": [
        {
            "reference": "Condition/Ty72I7hLQz",
            "type": "Condition",
            "identifier": {
                "use": "secondary",
                "type": {
                    "coding": [
                        {
                            "system": "XgULOjZRsx",
                            "version": "YKpr7QVsXx",
                            "code": "d8tos8K8Nz",
                            "display": "hbRgXVsorT",
                            "userSelected": true
                        }
                    ],
                    "text": "VDYUg6QbTG"
                },
                "system": "e0B_Vzb2p5",
                "value": "yKOS7Lmcqk",
                "period": {
                    "start": "2021-03-29T10:12:04.986148-04:00",
                    "end": "2021-03-29T10:12:04.98631-04:00"
                }
            },
            "display": "VZ7JG3xhqx"
        }
    ],
    "note": [
        {
            "authorString": "ItdQk681Uq",
            "time": "2021-03-29T10:12:04.986595-04:00",
            "text": "ARvT4INz_V"
        }
    ],
    "dosage": [
        {
            "sequence": 2097637538,
            "text": "DOmZGdXdgp",
            "additionalInstruction": [
                {
                    "coding": [
                        {
                            "system": "UzcUPXH8H9",
                            "version": "Z7Jt0gz_d7",
                            "code": "WuX1JcskKr",
                            "display": "DDfAqltMza",
                            "userSelected": true
                        }
                    ],
                    "text": "qL6RNQxfGJ"
                }
            ],
            "patientInstruction": "p9XnTXITpH",
            "timing": {
                "event": [
                    "2021-03-29T10:12:04.98742-04:00"
                ],
                "repeat": {
                    "boundsDuration": {
                        "value": 0.88089904043511146891631824473734013736248016357421875,
                        "comparator": "<",
                        "unit": "AsgGTvve0c",
                        "system": "http://unitsofmeasure.org",
                        "code": "h"
                    },
                    "count": 1872466260,
                    "countMax": 48067775,
                    "duration": 0.50814197747790157411174050139379687607288360595703125,
                    "durationMax": 0.54909771368877635655536550984834320843219757080078125,
                    "durationUnit": "min",
                    "frequency": 1707091879,
                    "frequencyMax": 1788218732,
                    "period": 0.74867763761619932072477467954740859568119049072265625,
                    "periodMax": 0.59539843256651270309021128923632204532623291015625,
                    "periodUnit": "s",
                    "dayOfWeek": [
                        "fri"
                    ],
                    "when": [
                        "PCM"
                    ]
                },
                "code": {
                    "coding": [
                        {
                            "system": "8JygIBBeNR",
                            "version": "xePzHJt8zB",
                            "code": "N_hm3Nnwyv",
                            "display": "1LRNT0e_AU",
                            "userSelected": true
                        }
                    ],
                    "text": "pZFSJkFHFO"
                }
            },
            "asNeededCodeableConcept": {
                "coding": [
                    {
                        "system": "Ay7VmBbaFC",
                        "version": "qUkpn547R5",
                        "code": "u2D9yatTFd",
                        "display": "FCUUQHEVEe",
                        "userSelected": true
                    }
                ],
                "text": "lebblAlFKV"
            },
            "site": {
                "coding": [
                    {
                        "system": "SPwCgL1WhY",
                        "version": "lCrXMdjPi9",
                        "code": "cCZT0C82zs",
                        "display": "jKrpR990nK",
                        "userSelected": true
                    }
                ],
                "text": "K1vFDkqPDG"
            },
            "route": {
                "coding": [
                    {
                        "system": "WJko_VeuZh",
                        "version": "VPynQ8sfLF",
                        "code": "9j1GOOCJfb",
                        "display": "tzq0XxEa4R",
                        "userSelected": true
                    }
                ],
                "text": "boB5P9KN4q"
            },
            "method": {
                "coding": [
                    {
                        "system": "4q8Rb939AN",
                        "version": "FPWLMNzJPq",
                        "code": "MazHzCacWy",
                        "display": "7qkIdWe0nn",
                        "userSelected": true
                    }
                ],
                "text": "DveJ6nAsnp"
            },
            "doseAndRate": [
                {
                    "type": {
                        "coding": [
                            {
                                "system": "xAL2L7ZEFT",
                                "version": "VwHFizorhM",
                                "code": "iBz4LpKMWX",
                                "display": "MId9ZNvMOD",
                                "userSelected": true
                            }
                        ],
                        "text": "kXMQzgWDSG"
                    },
                    "doseQuantity": {
                        "value": 0.495894855826555513989006840347428806126117706298828125,
                        "unit": "8ql0frK9uz",
                        "system": "yQIbdDf5Hl",
                        "code": "Tc0cRHGrBM"
                    },
                    "rateRatio": {
                        "numerator": {
                            "value": 0.232410577094674886122760426587774418294429779052734375,
                            "comparator": ">",
                            "unit": "url5MVHlOZ",
                            "system": "t60x7HgOJe",
                            "code": "813viH8NEd"
                        },
                        "denominator": {
                            "value": 0.64550368507359678904578004221548326313495635986328125,
                            "comparator": ">",
                            "unit": "29DZzEzffd",
                            "system": "cXZzdQLR1i",
                            "code": "ez8V_qf2HE"
                        }
                    }
                }
            ],
            "maxDosePerPeriod": {
                "numerator": {
                    "value": 0.2242183577815064221550045431285980157554149627685546875,
                    "comparator": "<",
                    "unit": "VPFn6wY47E",
                    "system": "lvJcH1S5Dg",
                    "code": "FLTMQh_eUw"
                },
                "denominator": {
                    "value": 0.55806527088479374043572533992119133472442626953125,
                    "comparator": ">=",
                    "unit": "MHcIAVWaNJ",
                    "system": "nGNIqshuIg",
                    "code": "5oPchFoFyY"
                }
            },
            "maxDosePerAdministration": {
                "value": 0.824659155615398820060590878711082041263580322265625,
                "unit": "rgICXhsfrC",
                "system": "BTwmY2Yxuu",
                "code": "FchTYb_bJG"
            },
            "maxDosePerLifetime": {
                "value": 0.4695944719908720088596965069882571697235107421875,
                "unit": "9lz7FXL4Mi",
                "system": "fEo94l9P44",
                "code": "xl2uEajpKg"
            }
        }
    ]
}