{
    "resourceType": "Observation",
    "meta": {
        "versionId": "J6V-YiYNb0",
        "lastUpdated": "2020-11-04T02:37:46.45353-05:00",
        "source": "VrAopTf9CE",
        "profile": [
            "Yc1A_UFTUW"
        ],
        "security": [
            {
                "system": "VOMnJAfdMG",
                "version": "Pjaw0qu4j2",
                "code": "dSscbzYuNO",
                "display": "7FLm8_QMmi",
                "userSelected": true
            }
        ],
        "tag": [
            {
                "system": "864bhYt1oU",
                "version": "0tBqKiaAQA",
                "code": "08O9gP1MWb",
                "display": "vaJSRZHOJN",
                "userSelected": true
            },
            {
                "code": "ibm/complete-mock"
            }
        ]
    },
    "implicitRules": "LJxsilLPdj",
    "language": "en-US",
    "text": {
        "status": "empty",
        "div": "<div xmlns=\"http://www.w3.org/1999/xhtml\"></div>"
    },
    "identifier": [
        {
            "use": "secondary",
            "type": {
                "coding": [
                    {
                        "system": "32FVm6n1Um",
                        "version": "stiUPQciGv",
                        "code": "YK5YqE1NdH",
                        "display": "340j8sxTSE",
                        "userSelected": true
                    }
                ],
                "text": "uSuj2vlBMb"
            },
            "system": "U9Z0WiosjC",
            "value": "41AEsOr7mi",
            "period": {
                "start": "2020-11-04T02:37:46.456162-05:00",
                "end": "2020-11-04T02:37:46.456329-05:00"
            }
        }
    ],
    "basedOn": [
        {
            "reference": "ServiceRequest/XfRIZoYvnr",
            "type": "ServiceRequest",
            "identifier": {
                "use": "usual",
                "type": {
                    "coding": [
                        {
                            "system": "UfKHP_Swfd",
                            "version": "WKV0pVZuB8",
                            "code": "MIDtNbvGrC",
                            "display": "AsEJqK2MUL",
                            "userSelected": true
                        }
                    ],
                    "text": "1_5O7ATay0"
                },
                "system": "16fkdfcACa",
                "value": "lcPzYXlcLN",
                "period": {
                    "start": "2020-11-04T02:37:46.457164-05:00",
                    "end": "2020-11-04T02:37:46.457304-05:00"
                }
            },
            "display": "UNxYhnVbQE"
        }
    ],
    "partOf": [
        {
            "reference": "ImagingStudy/ryOFSJ049a",
            "type": "ImagingStudy",
            "identifier": {
                "use": "usual",
                "type": {
                    "coding": [
                        {
                            "system": "NvEEoEWino",
                            "version": "LWQPLrKInb",
                            "code": "b3_vYf7ucS",
                            "display": "BAIVjcCV8g",
                            "userSelected": true
                        }
                    ],
                    "text": "39iP4qxSm_"
                },
                "system": "sJkh9DZHNe",
                "value": "K7Z8rQXU9g",
                "period": {
                    "start": "2020-11-04T02:37:46.458146-05:00",
                    "end": "2020-11-04T02:37:46.458283-05:00"
                }
            },
            "display": "Cipgjli38g"
        }
    ],
    "status": "corrected",
    "category": [
        {
            "coding": [
                {
                    "system": "7gnbtRHCzk",
                    "version": "_5sNmkqBPQ",
                    "code": "Bv9dn4YgWy",
                    "display": "5RRMPpC8VJ",
                    "userSelected": true
                }
            ],
            "text": "WN8UhvDpgC"
        }
    ],
    "code": {
        "coding": [
            {
                "system": "gBHnt8uJ37",
                "version": "82nTGbGusG",
                "code": "QvvPu2Fdtk",
                "display": "Ra3IrXLhUw",
                "userSelected": true
            }
        ],
        "text": "QX2dHgSbC8"
    },
    "subject": {
        "reference": "Location/aHrQhrWHZj",
        "type": "Location",
        "identifier": {
            "use": "temp",
            "type": {
                "coding": [
                    {
                        "system": "IZvVOeKflj",
                        "version": "sqpUP_CU5q",
                        "code": "u598LDG3p4",
                        "display": "JVVV_NeHpv",
                        "userSelected": true
                    }
                ],
                "text": "tDn39KsXeh"
            },
            "system": "9mqx6zYli5",
            "value": "sbVUVofSmN",
            "period": {
                "start": "2020-11-04T02:37:46.459965-05:00",
                "end": "2020-11-04T02:37:46.460141-05:00"
            }
        },
        "display": "rMuKFuyZA7"
    },
    "focus": [
        {
            "reference": "Basic/z_dgSXWxUI",
            "type": "Basic",
            "identifier": {
                "use": "official",
                "type": {
                    "coding": [
                        {
                            "system": "1N3i7Mn2ki",
                            "version": "QW6cP9wDDJ",
                            "code": "pMIKbGSMHq",
                            "display": "rmduGuxGSM",
                            "userSelected": true
                        }
                    ],
                    "text": "khdHM31Wt5"
                },
                "system": "jWCbMkRXPF",
                "value": "XbNZRgwxt9",
                "period": {
                    "start": "2020-11-04T02:37:46.461009-05:00",
                    "end": "2020-11-04T02:37:46.461152-05:00"
                }
            },
            "display": "3mYgfSvKwN"
        }
    ],
    "encounter": {
        "reference": "Encounter/3aG1Auvm5Z",
        "type": "Encounter",
        "identifier": {
            "use": "temp",
            "type": {
                "coding": [
                    {
                        "system": "E_QPR9FpX5",
                        "version": "Rha1_DpUX0",
                        "code": "bKDTCQpNCe",
                        "display": "J5TBqaGQas",
                        "userSelected": true
                    }
                ],
                "text": "35FiyEM31x"
            },
            "system": "WZSVVMityq",
            "value": "4w7BVUWtIs",
            "period": {
                "start": "2020-11-04T02:37:46.462249-05:00",
                "end": "2020-11-04T02:37:46.462439-05:00"
            }
        },
        "display": "cdOcQ7hEow"
    },
    "effectiveInstant": "2020-11-04T02:37:46.462675-05:00",
    "issued": "2020-11-04T02:37:46.462837-05:00",
    "performer": [
        {
            "reference": "RelatedPerson/U5j_MFLqec",
            "type": "RelatedPerson",
            "identifier": {
                "use": "usual",
                "type": {
                    "coding": [
                        {
                            "system": "GTvohrw_VF",
                            "version": "w1dp8gWD_T",
                            "code": "aHw5fyBSRb",
                            "display": "NZuQBg5A3b",
                            "userSelected": true
                        }
                    ],
                    "text": "aTuD1RAl1t"
                },
                "system": "QeDA6IBV70",
                "value": "myL8oFriKe",
                "period": {
                    "start": "2020-11-04T02:37:46.463996-05:00",
                    "end": "2020-11-04T02:37:46.464155-05:00"
                }
            },
            "display": "IYMGzcJbsD"
        }
    ],
    "valueString": "5JbSgbr7EI",
    "interpretation": [
        {
            "coding": [
                {
                    "system": "lQekFqpWS6",
                    "version": "2pyTTad_io",
                    "code": "MWXNwjwIiZ",
                    "display": "_w_ba1O92j",
                    "userSelected": true
                }
            ],
            "text": "a_SrgqotcH"
        }
    ],
    "note": [
        {
            "authorString": "xgTcN4jN7A",
            "time": "2020-11-04T02:37:46.464887-05:00",
            "text": "KS7gkBDL5O"
        }
    ],
    "bodySite": {
        "coding": [
            {
                "system": "djqBNwdhFr",
                "version": "LFyvcrVC7W",
                "code": "d8spSfxaKq",
                "display": "4SHLYudX9W",
                "userSelected": true
            }
        ],
        "text": "KYci1_D6rz"
    },
    "method": {
        "coding": [
            {
                "system": "N7bDPjW2dA",
                "version": "y0Uus_rDqp",
                "code": "rMZc5K2cBW",
                "display": "MYbw03tIig",
                "userSelected": true
            }
        ],
        "text": "gxw6iE7UL8"
    },
    "specimen": {
        "reference": "Specimen/3bKrcfEYJU",
        "type": "Specimen",
        "identifier": {
            "use": "secondary",
            "type": {
                "coding": [
                    {
                        "system": "GWbeg4isEh",
                        "version": "YgneJpIS_7",
                        "code": "tcHQ1BH9Qu",
                        "display": "7MBcimWdTj",
                        "userSelected": true
                    }
                ],
                "text": "LAups9vVko"
            },
            "system": "Xuf7Vcwazw",
            "value": "rl2LaDV8lQ",
            "period": {
                "start": "2020-11-04T02:37:46.466566-05:00",
                "end": "2020-11-04T02:37:46.46672-05:00"
            }
        },
        "display": "NBfVcIgNHk"
    },
    "device": {
        "reference": "DeviceMetric/8ojlYBMKoj",
        "type": "DeviceMetric",
        "identifier": {
            "use": "old",
            "type": {
                "coding": [
                    {
                        "system": "XEkn9D4IA7",
                        "version": "_pRk9m8KUf",
                        "code": "WoQrifgdN2",
                        "display": "JiNGI4mR0B",
                        "userSelected": true
                    }
                ],
                "text": "wsdOd6XTML"
            },
            "system": "JquLOC4823",
            "value": "AXkVxQHXVk",
            "period": {
                "start": "2020-11-04T02:37:46.467627-05:00",
                "end": "2020-11-04T02:37:46.467773-05:00"
            }
        },
        "display": "MdMPGM5M6Y"
    },
    "referenceRange": [
        {
            "low": {
                "value": 0.066827046596373784748124080579145811498165130615234375,
                "unit": "BNVE1ztuPs",
                "system": "KOXRNGOgsd",
                "code": "ll4U6BYg_g"
            },
            "high": {
                "value": 0.225808583745020385880053481741924770176410675048828125,
                "unit": "yS8ZkYqb7o",
                "system": "yfl2ARHef0",
                "code": "U7vEs8j5qo"
            },
            "type": {
                "coding": [
                    {
                        "system": "INHVkW_iED",
                        "version": "Lim_SSJu5e",
                        "code": "TztXSc2Ibu",
                        "display": "sYNkae3Mln",
                        "userSelected": true
                    }
                ],
                "text": "zqx8eWYciu"
            },
            "appliesTo": [
                {
                    "coding": [
                        {
                            "system": "Uu9UjB4K9_",
                            "version": "lZHmxFiTzK",
                            "code": "zQo55Azk_n",
                            "display": "6Ax1iXGPmB",
                            "userSelected": true
                        }
                    ],
                    "text": "8sz4CfmxAm"
                }
            ],
            "age": {
                "low": {
                    "value": 0.276609123428247727360940189100801944732666015625,
                    "unit": "L0SgOeivlX",
                    "system": "70B8c2Sxhe",
                    "code": "ebL9BurCug"
                }
            },
            "text": "OiMkQxsOeB"
        }
    ],
    "hasMember": [
        {
            "reference": "MolecularSequence/AcN6PkbPk4",
            "type": "MolecularSequence",
            "identifier": {
                "use": "secondary",
                "type": {
                    "coding": [
                        {
                            "system": "HHt9ZR9HuO",
                            "version": "nbiUpNzks3",
                            "code": "wTUAd69rnd",
                            "display": "hUmN06DsIq",
                            "userSelected": true
                        }
                    ],
                    "text": "BnrXXwGMmV"
                },
                "system": "XQNsrnOwu2",
                "value": "vGV8HNEu_y",
                "period": {
                    "start": "2020-11-04T02:37:46.471409-05:00",
                    "end": "2020-11-04T02:37:46.471589-05:00"
                }
            },
            "display": "huw7cziAl3"
        }
    ],
    "derivedFrom": [
        {
            "reference": "MolecularSequence/uOie1Ro_6p",
            "type": "MolecularSequence",
            "identifier": {
                "use": "temp",
                "type": {
                    "coding": [
                        {
                            "system": "TrJ8jImSJk",
                            "version": "PyHDTrI3p4",
                            "code": "ebC7Gxn2mY",
                            "display": "l9vBd5kQUq",
                            "userSelected": true
                        }
                    ],
                    "text": "KjO9D2Pulq"
                },
                "system": "2aWSzjH0Pa",
                "value": "nAV6HVLhAF",
                "period": {
                    "start": "2020-11-04T02:37:46.472681-05:00",
                    "end": "2020-11-04T02:37:46.472834-05:00"
                }
            },
            "display": "DcxDDBX2sa"
        }
    ],
    "component": [
        {
            "code": {
                "coding": [
                    {
                        "system": "ttcUAAeVyj",
                        "version": "P2J3gKSqK6",
                        "code": "FRNtOSnccp",
                        "display": "GMPSS_Gsyl",
                        "userSelected": true
                    }
                ],
                "text": "5dndhyaQMh"
            },
            "valueString": "0f3llpBBQh",
            "dataAbsentReason": {
                "coding": [
                    {
                        "system": "KxWdgRPkqP",
                        "version": "HmooSgZ2Jc",
                        "code": "ATTxFDTs5S",
                        "display": "TauZkEwGNg",
                        "userSelected": true
                    }
                ],
                "text": "GWE7iaFHOy"
            },
            "interpretation": [
                {
                    "coding": [
                        {
                            "system": "QfR0nMZ5hj",
                            "version": "ulVNNIyTRI",
                            "code": "2y197834fW",
                            "display": "amQ8NFjBtS",
                            "userSelected": true
                        }
                    ],
                    "text": "kvp3J1lIUN"
                }
            ],
            "referenceRange": [
                {
                    "low": {
                        "value": 0.21709746069230762000046297544031403958797454833984375,
                        "unit": "qa2m1fqFRQ",
                        "system": "lNDYZa_VQ_",
                        "code": "wK53hbKc6C"
                    },
                    "high": {
                        "value": 0.0309170684947890038463125250700613833032548427581787109375,
                        "unit": "t4mdNsLTRI",
                        "system": "7XdD7eHUMW",
                        "code": "SpTEDQ0usj"
                    },
                    "type": {
                        "coding": [
                            {
                                "system": "6v8ko0Epcd",
                                "version": "RQemdSpvlX",
                                "code": "FOqCKjvoPf",
                                "display": "DCQWlNJLoN",
                                "userSelected": true
                            }
                        ],
                        "text": "_2NE5BCMDl"
                    },
                    "appliesTo": [
                        {
                            "coding": [
                                {
                                    "system": "XAeYf8n11_",
                                    "version": "_uTR6_pPPM",
                                    "code": "zDx2Bq7qYY",
                                    "display": "xBhLY0KuEF",
                                    "userSelected": true
                                }
                            ],
                            "text": "xlaf46XDR8"
                        }
                    ],
                    "age": {
                        "low": {
                            "value": 0.64792399499805763962712035208824090659618377685546875,
                            "unit": "L44oHBJiAv",
                            "system": "ZVt_7zywgL",
                            "code": "n5az_WnhoA"
                        }
                    },
                    "text": "ERr72U4NS0"
                }
            ]
        }
    ]
}