<server description="fhir-server">

    <!-- Enable features -->
    <featureManager>
        <!-- mpJwt-1.2 is already enabled in the default server.xml, but it doesn't hurt to repeat it here -->
        <feature>mpJwt-1.2</feature>
    </featureManager>

    <!-- Override the application-bnd binding of the main webapp -->
    <webApplication contextRoot="fhir-server/api/v4" id="fhir-server-webapp" location="fhir-server.war" name="fhir-server-webapp">
        <application-bnd id="bind">
            <security-role id="users" name="FHIRUsers">
                <group id="usersGroup" access-id="group:https://localhost:8443/auth/realms/master/inferno"/>
            </security-role>
        </application-bnd>
    </webApplication>
    
    <!-- The MP JWT configuration that injects the caller's JWT into a
         ResourceScoped bean for inspection. -->
    <mpJwt id="jwtConsumer"
           jwksUri="http://localhost:8080/auth/realms/master/protocol/openid-connect/certs"
           audiences="https://localhost:9443/fhir-server/api/v4"
           userNameAttribute="sub"
           groupNameAttribute="azp"
           issuer="https://localhost:8443/auth/realms/master"
           signatureAlgorithm="RS256"
           authFilterRef="filter"/>

    <authFilter id="filter">
        <requestUrl urlPattern="/fhir-server" />
    </authFilter>
</server>