<?xml version="1.0" encoding="UTF-8"?>

<ConceptMap xmlns="http://hl7.org/fhir">
  <id value="sc-subscription-status"/>
  <text>
    <status value="extensions"/>
    <div xmlns="http://www.w3.org/1999/xhtml">
      <h2>SubscriptionStatusCodesCanonicalMap (http://hl7.org/fhir/ConceptMap/sc-subscription-status)</h2>
      <p>Mapping from 
        <a href="valueset-subscription-status.html">http://hl7.org/fhir/ValueSet/subscription-status</a> to 
        <a href="valueset-resource-status.html">http://hl7.org/fhir/ValueSet/resource-status</a>
      </p>
      <p>DRAFT. Published on 2021-01-16T20:06:13Z by HL7 (FHIR Project) (
        <a href="http://hl7.org/fhir">http://hl7.org/fhir</a>, 
        <a href="mailto:fhir@lists.hl7.org">fhir@lists.hl7.org</a>). 
      </p>
      <div>
        <p>Canonical Mapping for &quot;The status of a subscription.&quot;</p>

      </div>
      <br/>
      <table class="grid">
        <tr>
          <td>
            <b>Source Code</b>
          </td>
          <td>
            <b>Relationship</b>
          </td>
          <td>
            <b>Destination Code</b>
          </td>
        </tr>
        <tr>
          <td colspan="3">Mapping from 
            <a href="codesystem-subscription-status.html">SubscriptionStatus</a> to 
            <a href="codesystem-resource-status.html">Canonical Status Codes for FHIR Resources</a>
          </td>
        </tr>
        <tr>
          <td>requested</td>
          <td>
            <a href="codesystem-concept-map-equivalence.html#equivalent">is equivalent to</a>
          </td>
          <td>requested</td>
        </tr>
        <tr>
          <td>active</td>
          <td>
            <a href="codesystem-concept-map-equivalence.html#equivalent">is equivalent to</a>
          </td>
          <td>active</td>
        </tr>
        <tr>
          <td>error</td>
          <td>
            <a href="codesystem-concept-map-equivalence.html#equivalent">is equivalent to</a>
          </td>
          <td>failed</td>
        </tr>
        <tr>
          <td>off</td>
          <td>
            <a href="codesystem-concept-map-equivalence.html#equivalent">is equivalent to</a>
          </td>
          <td>inactive</td>
        </tr>
      </table>
    </div>
  </text>
  <url value="http://hl7.org/fhir/ConceptMap/sc-subscription-status"/>
  <version value="4.3.0-cibuild"/>
  <name value="SubscriptionStatusCodesCanonicalMap"/>
  <title value="Canonical Mapping for &quot;SubscriptionStatusCodes&quot;"/>
  <status value="draft"/>
  <experimental value="false"/>
  <date value="2021-01-16T20:06:13+00:00"/>
  <publisher value="HL7 (FHIR Project)"/>
  <contact>
    <telecom>
      <system value="url"/>
      <value value="http://hl7.org/fhir"/>
    </telecom>
    <telecom>
      <system value="email"/>
      <value value="fhir@lists.hl7.org"/>
    </telecom>
  </contact>
  <description value="Canonical Mapping for &quot;The status of a subscription.&quot;"/>
  <sourceCanonical value="http://hl7.org/fhir/ValueSet/subscription-status"/>
  <targetCanonical value="http://hl7.org/fhir/ValueSet/resource-status"/>
  <group>
    <source value="http://hl7.org/fhir/subscription-status"/>
    <target value="http://hl7.org/fhir/resource-status"/>
    <element>
      <code value="requested"/>
      <target>
        <code value="requested"/>
        <equivalence value="equivalent"/>
      </target>
    </element>
    <element>
      <code value="active"/>
      <target>
        <code value="active"/>
        <equivalence value="equivalent"/>
      </target>
    </element>
    <element>
      <code value="error"/>
      <target>
        <code value="failed"/>
        <equivalence value="equivalent"/>
      </target>
    </element>
    <element>
      <code value="off"/>
      <target>
        <code value="inactive"/>
        <equivalence value="equivalent"/>
      </target>
    </element>
  </group>
</ConceptMap>