{
    "resourceType": "ValueSet",
    "id": "contributor-type",
    "meta": {
        "lastUpdated": "2022-03-03T22:04:06.196Z",
        "profile": [
            "http://hl7.org/fhir/StructureDefinition/shareablevalueset"
        ]
    },
    "extension": [
        {
            "url": "http://hl7.org/fhir/StructureDefinition/structuredefinition-wg",
            "valueCode": "fhir"
        },
        {
            "url": "http://hl7.org/fhir/StructureDefinition/structuredefinition-standards-status",
            "valueCode": "trial-use"
        },
        {
            "url": "http://hl7.org/fhir/StructureDefinition/structuredefinition-fmm",
            "valueInteger": 5
        }
    ],
    "url": "http://hl7.org/fhir/ValueSet/contributor-type",
    "identifier": [
        {
            "system": "urn:ietf:rfc:3986",
            "value": "urn:oid:2.16.840.1.113883.4.642.3.93"
        }
    ],
    "version": "4.3.0-CIBUILD",
    "name": "ContributorType",
    "title": "ContributorType",
    "status": "draft",
    "experimental": false,
    "date": "2022-03-03T22:04:06Z",
    "publisher": "HL7 (FHIR Project)",
    "contact": [
        {
            "telecom": [
                {
                    "system": "url",
                    "value": "http://hl7.org/fhir"
                },
                {
                    "system": "email",
                    "value": "fhir@lists.hl7.org"
                }
            ]
        }
    ],
    "description": "The type of contributor.",
    "immutable": true,
    "compose": {
        "include": [
            {
                "system": "http://hl7.org/fhir/contributor-type"
            }
        ]
    },
    "expansion": {
        "identifier": "urn:uuid:12f69417-bda3-437e-876e-c5b9755f93a3",
        "timestamp": "2022-03-03T22:05:09Z",
        "total": 4,
        "parameter": [
            {
                "name": "excludeNested",
                "valueBoolean": true
            },
            {
                "name": "includeDesignations",
                "valueBoolean": true
            },
            {
                "name": "version",
                "valueUri": "http://hl7.org/fhir/contributor-type|4.3.0-CIBUILD"
            }
        ],
        "contains": [
            {
                "system": "http://hl7.org/fhir/contributor-type",
                "code": "author",
                "display": "Author"
            },
            {
                "system": "http://hl7.org/fhir/contributor-type",
                "code": "editor",
                "display": "Editor"
            },
            {
                "system": "http://hl7.org/fhir/contributor-type",
                "code": "reviewer",
                "display": "Reviewer"
            },
            {
                "system": "http://hl7.org/fhir/contributor-type",
                "code": "endorser",
                "display": "Endorser"
            }
        ]
    }
}